funcnodes_microscopy/SEM.py
funcnodes_microscopy/__init__.py
funcnodes_microscopy/_circles.py
funcnodes_microscopy/_contours.py
funcnodes_microscopy/_resolution.py
funcnodes_microscopy/images.py
funcnodes_microscopy-0.1.0.dist-info/LICENSE
funcnodes_microscopy-0.1.0.dist-info/METADATA
funcnodes_microscopy-0.1.0.dist-info/WHEEL
funcnodes_microscopy-0.1.0.dist-info/entry_points.txt
funcnodes_microscopy-0.1.0.dist-info/top_level.txt
funcnodes_microscopy-0.1.0.dist-info/RECORD
